pastelaria.py
frameworks/__init__.py
frameworks/django/__init__.py
frameworks/fastapi/__init__.py
frameworks/fastapi/framework.py
frameworks/fastapi/utils.py
frameworks/fastapi/dbs/__init__.py
frameworks/fastapi/dbs/templates_mongo.py
frameworks/fastapi/dbs/templates_relational.py
frameworks/flask/__init__.py
pastelaria-0.0.1.dist-info/LICENSE
pastelaria-0.0.1.dist-info/METADATA
pastelaria-0.0.1.dist-info/WHEEL
pastelaria-0.0.1.dist-info/entry_points.txt
pastelaria-0.0.1.dist-info/top_level.txt
pastelaria-0.0.1.dist-info/RECORD
