Metadata-Version: 2.1
Name: pastelaria
Version: 0.0.1
Summary: CLI for generating API boilerplates
Home-page: https://github.com/thaisribeiro/pastelaria
Author: Thais Ribeiro
Author-email: thaisribeirodn@gmail.com
Classifier: Programming Language :: Python :: 3.10
Classifier: License :: OSI Approved :: MIT License
Classifier: Operating System :: OS Independent
Requires-Python: >=3.10
License-File: LICENSE
Requires-Dist: cutie (>=0.3.2)
Requires-Dist: click (==8.1.3)
